Metadata-Version: 1.0
Name: yayuchen
Version: 0.2
Summary: Gaussian distributions
Home-page: UNKNOWN
Author: Ya Yu Chen
Author-email: a725761@gmail.com
License: UNKNOWN
Platform: UNKNOWN
